Workbook

Sheet Products
A1: ProductID | B1: Manufacturer | C1: Model | D1: VehicleType | E1: EngineSize | F1: Horsepower | G1: FuelEfficiency | H1: Base Price | I1: Average product rating
A2: P001 | B2: Honda | C2: RAV4 | D2: SUV | E2: 4.1 | F2: 225 | G2: 22 | H2: 27144 | I2: =(F2/E2)*G2 -> 1207.3171
A3: P002 | B3: Honda | C3: Civic | D3: Hatchback | E3: 1.8 | F3: 316 | G3: 16 | H3: 19952 | I3: =(F3/E3)*G3 -> 2808.8889
A4: P003 | B4: Honda | C4: F-150 | D4: Sedan | E4: 2.3 | F4: 408 | G4: 15 | H4: 54781 | I4: =(F4/E4)*G4 -> 2660.8696
A5: P004 | B5: BMW | C5: X3 | D5: Hatchback | E5: 3 | F5: 329 | G5: 33 | H5: 36231 | I5: =(F5/E5)*G5 -> 3619
A6: P005 | B6: Toyota | C6: A5 | D6: Sedan | E6: 3.9 | F6: 274 | G6: 23 | H6: 28189 | I6: =(F6/E6)*G6 -> 1615.8974
A7: P006 | B7: BMW | C7: Tucson | D7: Truck | E7: 1.9 | F7: 294 | G7: 18 | H7: 41526 | I7: =(F7/E7)*G7 -> 2785.2632
A8: P007 | B8: Hyundai | C8: CX-5 | D8: Hatchback | E8: 2.4 | F8: 122 | G8: 38 | H8: 48108 | I8: =(F8/E8)*G8 -> 1931.6667
A9: P008 | B9: Nissan | C9: Malibu | D9: SUV | E9: 4.9 | F9: 293 | G9: 17 | H9: 54178 | I9: =(F9/E9)*G9 -> 1016.5306
A10: P009 | B10: Audi | C10: Altima | D10: Hatchback | E10: 4.6 | F10: 285 | G10: 33 | H10: 30601 | I10: =(F10/E10)*G10 -> 2044.5652
A11: P010 | B11: Honda | C11: C-Class | D11: SUV | E11: 3.8 | F11: 248 | G11: 17 | H11: 33256 | I11: =(F11/E11)*G11 -> 1109.4737
A12: P011 | B12: Honda | C12: Corolla | D12: Coupe | E12: 2.5 | F12: 425 | G12: 26 | H12: 28659 | I12: =(F12/E12)*G12 -> 4420
A13: P012 | B13: Hyundai | C13: Accord | D13: Truck | E13: 2.2 | F13: 236 | G13: 37 | H13: 22679 | I13: =(F13/E13)*G13 -> 3969.0909
... A21: P020 | B21: Ford | C21: GLA | D21: Hatchback | E21: 3.2 | F21: 124 | G21: 18 | H21: 28016 | I21: =(F21/E21)*G21 -> 697.5

Sheet Sales
A1: OrderID | B1: Date | C1: Customer | D1: City | E1: ProductID | F1: Quantity | G1: Discount | H1: PaymentMethod | I1: Revenue
A2: 1001 | B2: 2022-10-05 | C2: Frank | D2: Ottawa | E2: P014 | F2: 5 | G2: 0.01 | H2: Lease | I2: 269775
A3: 1002 | B3: 2022-09-03 | C3: Oscar | D3: Edmonton | E3: P009 | F3: 5 | G3: 0.13 | H3: Credit Card | I3: 133114.35
A4: 1003 | B4: 2022-11-28 | C4: David | D4: Ottawa | E4: P018 | F4: 3 | G4: 0.12 | H4: Financing | I4: 92978.16
A5: 1004 | B5: 2021-04-25 | C5: Jack | D5: Montreal | E5: P006 | F5: 4 | G5: 0 | H5: Financing | I5: 166104
A6: 1005 | B6: 2022-05-28 | C6: Frank | D6: Edmonton | E6: P004 | F6: 3 | G6: 0.13 | H6: Cash | I6: 94562.91
A7: 1006 | B7: 2021-06-06 | C7: Leo | D7: Toronto | E7: P018 | F7: 5 | G7: 0.14 | H7: Financing | I7: 151441.7
A8: 1007 | B8: 2022-05-16 | C8: Alice | D8: Calgary | E8: P012 | F8: 3 | G8: 0.04 | H8: Cash | I8: 65315.52
A9: 1008 | B9: 2022-08-04 | C9: Carol | D9: Calgary | E9: P016 | F9: 1 | G9: 0.15 | H9: Cash | I9: 32828.7
A10: 1009 | B10: 2021-05-12 | C10: Paul | D10: Edmonton | E10: P006 | F10: 3 | G10: 0.08 | H10: Lease | I10: 114611.76
A11: 1010 | B11: 2021-08-05 | C11: Rita | D11: Ottawa | E11: P007 | F11: 3 | G11: 0.06 | H11: Financing | I11: 135664.56
A12: 1011 | B12: 2022-03-25 | C12: Quinn | D12: Montreal | E12: P004 | F12: 2 | G12: 0.03 | H12: Financing | I12: 70288.14
A13: 1012 | B13: 2021-01-22 | C13: Sam | D13: Edmonton | E13: P008 | F13: 5 | G13: 0.03 | H13: Credit Card | I13: 262763.3
... A101: 1100 | B101: 2021-06-05 | C101: Emily | D101: Edmonton | E101: P010 | F101: 1 | G101: 0.15 | H101: Credit Card | I101: 28267.6

Sheet Homework 5 Basic Functions
B2: Basic Functions
B4: Total revenue | C4: Highest prices | D4: lowest prices | E4: Average product rating
B5: =SUM(Sales!I2:I101) -> 10232424 | C5: =MAX(Products!H2:H21) -> 54781 | D5: =MIN(Products!H2:H21) -> 19952 | E5: =AVERAGEA(Products!I2:I21) -> 2451.8827
E6: =AVERAGE(Products!G2:G21) -> 25.6

Sheet Conditional Functions
B2: Conditional Functions
B3: SUMIF, COUNTIF, AVERAGEIF
B5: Total top orders | C5: =SUMIF(Sales!I2:I101,">"&AVERAGEIF(Sales!I2:I101,">0"),Sales!I2:I101) -> 6824911.5
B6: Number of orders with the highest revenue | C6: =COUNTIF(Sales!I2:I101,">"&AVERAGEIF(Sales!I2:I101,">0")) -> 43
B7: Average top revenue | C7: =AVERAGEIF(Sales!I2:I101,">"&AVERAGEIF(Sales!I2:I101,">0")) -> 158718.87

Sheet Lookup Functions
B2: Lookup Functions
B5: {=VLOOKUP(Products!A1:A21,Products!A1:D21,4,FALSE)} -> VehicleType | D5: =_xlfn.XLOOKUP(Products!B2,Products!A1:A21,Products!B1:B22) -> #VALUE!
B6: SUV
B7: Hatchback
B8: Sedan
B9: Hatchback
B10: Sedan
B11: Truck
B12: Hatchback
B13: SUV
B14: Hatchback
B15: SUV
B16: Coupe
B17: Truck
... B25: Hatchback

Sheet PivotTables
A1: OrderID | B1: Date | C1: Customer | D1: City | E1: ProductID | F1: Category | G1: Quantity | H1: Discount | I1: PaymentMethod | J1: Revenue
A2: 1001 | B2: 2022-10-05 | C2: Frank | D2: Ottawa | E2: P014 | G2: 5 | H2: 0.01 | I2: Lease | J2: 269775
A3: 1002 | B3: 2022-09-03 | C3: Oscar | D3: Edmonton | E3: P009 | G3: 5 | H3: 0.13 | I3: Credit Card | J3: 133114.35
A4: 1003 | B4: 2022-11-28 | C4: David | D4: Ottawa | E4: P018 | G4: 3 | H4: 0.12 | I4: Financing | J4: 92978.16
A5: 1004 | B5: 2021-04-25 | C5: Jack | D5: Montreal | E5: P006 | G5: 4 | H5: 0 | I5: Financing | J5: 166104
A6: 1005 | B6: 2022-05-28 | C6: Frank | D6: Edmonton | E6: P004 | G6: 3 | H6: 0.13 | I6: Cash | J6: 94562.91
A7: 1006 | B7: 2021-06-06 | C7: Leo | D7: Toronto | E7: P018 | G7: 5 | H7: 0.14 | I7: Financing | J7: 151441.7
A8: 1007 | B8: 2022-05-16 | C8: Alice | D8: Calgary | E8: P012 | G8: 3 | H8: 0.04 | I8: Cash | J8: 65315.52
A9: 1008 | B9: 2022-08-04 | C9: Carol | D9: Calgary | E9: P016 | G9: 1 | H9: 0.15 | I9: Cash | J9: 32828.7
A10: 1009 | B10: 2021-05-12 | C10: Paul | D10: Edmonton | E10: P006 | G10: 3 | H10: 0.08 | I10: Lease | J10: 114611.76
A11: 1010 | B11: 2021-08-05 | C11: Rita | D11: Ottawa | E11: P007 | G11: 3 | H11: 0.06 | I11: Financing | J11: 135664.56
A12: 1011 | B12: 2022-03-25 | C12: Quinn | D12: Montreal | E12: P004 | G12: 2 | H12: 0.03 | I12: Financing | J12: 70288.14
A13: 1012 | B13: 2021-01-22 | C13: Sam | D13: Edmonton | E13: P008 | G13: 5 | H13: 0.03 | I13: Credit Card | J13: 262763.3
... A101: 1100 | B101: 2021-06-05 | C101: Emily | D101: Edmonton | E101: P010 | G101: 1 | H101: 0.15 | I101: Credit Card | J101: 28267.6
